{
  "id": "info:root/tinder.3/tinder.3.tinder-rppc-000006-Y-HXkA~md.json",
  "parent": "info:root/tinder.3",
  "systemIdentifier": "35ee7338-74c1-5e76-86b6-91e4cec79b66",
  "interactionModel": "urn:umich:lib:dor:model:2026:file:metadata",
  "contentSize": 58,
  "mimeType": "application/dc+json",
  "filename": "tinder.3.tinder-rppc-000006-Y-HXkA~md.json",
  "digests": [
    "urn:sha-512:afa486b752dd6f7887afb4523a628bddc5f890a9b75dcd2277c46b06dc48be1c71326ba69ed88be30bac451e6896a55714561930bc8d9d9c0323091fd5b5059d"
  ],
  "updatedAt": "2025-11-05T15:34:56-05:00",
  "updatedBy": "dlxsadm",
  "deleted": false,
  "visibility": "visible",
  "contentPath": "tinder.3.tinder-rppc-000006-Y-HXkA~md.json",
  "headersVersion": "1.0"
}